AUTHORS.rst
CONTRIBUTING.rst
HISTORY.rst
LICENSE
MANIFEST.in
README.rst
setup.cfg
setup.py
chinadailyproject/__init__.py
chinadailyproject/chinadailyproject.py
chinadailyproject/cli.py
chinadailyproject.egg-info/PKG-INFO
chinadailyproject.egg-info/SOURCES.txt
chinadailyproject.egg-info/dependency_links.txt
chinadailyproject.egg-info/entry_points.txt
chinadailyproject.egg-info/not-zip-safe
chinadailyproject.egg-info/top_level.txt
docs/Makefile
docs/authors.rst
docs/conf.py
docs/contributing.rst
docs/history.rst
docs/index.rst
docs/installation.rst
docs/make.bat
docs/readme.rst
docs/usage.rst
tests/__init__.py
tests/test_chinadailyproject.py